devstash/__init__.py
devstash/__main__.py
devstash/_ast_rewrite.py
devstash/_cache.py
devstash/cli.py
devstash-0.1.1.dist-info/licenses/LICENSE
devstash-0.1.1.dist-info/METADATA
devstash-0.1.1.dist-info/WHEEL
devstash-0.1.1.dist-info/entry_points.txt
devstash-0.1.1.dist-info/top_level.txt
devstash-0.1.1.dist-info/RECORD
