Metadata-Version: 2.4
Name: devstash
Version: 0.1.1
Summary: Development-time persistent caching for function calls and variables, to speed up iteration and save money on APIs.
Author-email: Chris Brookes <chrisb856@gmail.com>
License: MIT
Project-URL: Homepage, https://github.com/chrisBrookes93/devstash
Project-URL: Repository, https://github.com/chrisBrookes93/devstash
Project-URL: Issues, https://github.com/chrisBrookes93/devstash/issues
Keywords: caching,development,debugging,llm,api,productivity
Classifier: Development Status :: 3 - Alpha
Classifier: Intended Audience :: Developers
Classifier: License :: OSI Approved :: MIT License
Classifier: Programming Language :: Python
Classifier: Programming Language :: Python :: 3
Classifier: Programming Language :: Python :: 3.9
Classifier: Programming Language :: Python :: 3.10
Classifier: Programming Language :: Python :: 3.11
Classifier: Programming Language :: Python :: 3.12
Classifier: Programming Language :: Python :: 3.13
Classifier: Topic :: Software Development :: Libraries
Classifier: Topic :: Utilities
Requires-Python: >=3.9
License-File: LICENSE
Dynamic: license-file
